<annotation>
	<folder></folder>
	<filename>image-142-90_jpg.rf.a1e92cee5b2717aece958beccff6e459.jpg</filename>
	<path>image-142-90_jpg.rf.a1e92cee5b2717aece958beccff6e459.jpg</path>
	<source>
		<database>roboflow.ai</database>
	</source>
	<size>
		<width>640</width>
		<height>640</height>
		<depth>3</depth>
	</size>
	<segmented>0</segmented>
	<object>
		<name>number-of-bus</name>
		<pose>Unspecified</pose>
		<truncated>0</truncated>
		<difficult>0</difficult>
		<occluded>0</occluded>
		<bndbox>
			<xmin>276</xmin>
			<xmax>302</xmax>
			<ymin>346</ymin>
			<ymax>376</ymax>
		</bndbox>
	</object>
</annotation>
