<annotation>
	<folder></folder>
	<filename>image-566-55_jpg.rf.926018c0e3dbf1d9737bcc63ad93707e.jpg</filename>
	<path>image-566-55_jpg.rf.926018c0e3dbf1d9737bcc63ad93707e.jpg</path>
	<source>
		<database>roboflow.ai</database>
	</source>
	<size>
		<width>640</width>
		<height>640</height>
		<depth>3</depth>
	</size>
	<segmented>0</segmented>
	<object>
		<name>number-of-bus</name>
		<pose>Unspecified</pose>
		<truncated>0</truncated>
		<difficult>0</difficult>
		<occluded>0</occluded>
		<bndbox>
			<xmin>250</xmin>
			<xmax>271</xmax>
			<ymin>342</ymin>
			<ymax>381</ymax>
		</bndbox>
	</object>
</annotation>
